LICENSE
MANIFEST.in
README.md
setup.py
ModelTracker/Tracker.py
ModelTracker/__init__.py
ModelTracker/middleware.py
ModelTracker/models.py
ModelTracker/urls.py
ModelTracker/views.py
ModelTracker/management/__init__.py
ModelTracker/management/commands/__init__.py
ModelTracker/management/commands/restoreObject.py
ModelTracker/migrations/0001_initial.py
ModelTracker/migrations/0002_auto_20160929_0517.py
ModelTracker/migrations/0003_history_related_objects.py
ModelTracker/migrations/__init__.py
ModelTracker/static/ModelTracker/bootstrap.min.css
ModelTracker/static/ModelTracker/jquery-3.2.1.min.js
ModelTracker/templates/changes.html
ModelTracker/templates/main.html
django_model_tracker.egg-info/PKG-INFO
django_model_tracker.egg-info/SOURCES.txt
django_model_tracker.egg-info/dependency_links.txt
django_model_tracker.egg-info/not-zip-safe
django_model_tracker.egg-info/requires.txt
django_model_tracker.egg-info/top_level.txt